map_merge.py
map_merge-0.0.1.dist-info/top_level.txt
map_merge-0.0.1.dist-info/METADATA
map_merge-0.0.1.dist-info/DESCRIPTION.rst
map_merge-0.0.1.dist-info/LICENSE.txt
map_merge-0.0.1.dist-info/metadata.json
map_merge-0.0.1.dist-info/WHEEL
map_merge-0.0.1.dist-info/RECORD
